[{"name": "Albums", "dir": true, "empty": true, "size": 0}, {"name": "Albums/1 featured", "dir": true, "empty": true, "size": 0}, {"name": "Albums/2 enzo", "dir": true, "empty": true, "size": 0}, {"name": "Albums/3 people", "dir": true, "empty": true, "size": 0}, {"name": "Albums/4 cool photos", "dir": true, "empty": true, "size": 0}, {"name": "Albums/5 petnica", "dir": true, "empty": true, "size": 0}, {"name": "Albums/6 Film photos", "dir": true, "empty": true, "size": 0}, {"name": "Albums/7 blokade", "dir": true, "empty": true, "size": 0}, {"name": "Albums/8 iPhone", "dir": true, "empty": true, "size": 0}, {"name": "assets", "dir": true, "empty": true, "size": 0}, {"name": "assets/attic", "dir": true, "empty": true, "size": 0}, {"name": "assets/banner", "dir": true, "empty": true, "size": 0}, {"name": "assets/banner/.old", "dir": true, "empty": true, "size": 0}, {"name": "assets/gear", "dir": true, "empty": true, "size": 0}, {"name": "assets/ltremark", "dir": true, "empty": true, "size": 0}, {"name": "assets/other fonts", "dir": true, "empty": true, "size": 0}, {"name": "assets/photos", "dir": true, "empty": true, "size": 0}, {"name": "assets/redaction", "dir": true, "empty": true, "size": 0}, {"name": "cloudflare", "dir": true, "empty": true, "size": 0}, {"name": "cloudflare/.wrangler", "dir": true, "empty": true, "size": 0}, {"name": "cloudflare/.wrangler/cache", "dir": true, "empty": true, "size": 0}, {"name": "cloudflare/.wrangler/state", "dir": true, "empty": true, "size": 0}, {"name": "cloudflare/.wrangler/state/v3", "dir": true, "empty": true, "size": 0}, {"name": "cloudflare/.wrangler/state/v3/d1", "dir": true, "empty": true, "size": 0}, {"name": "cloudflare/.wrangler/state/v3/d1/miniflare-D1DatabaseObject", "dir": true, "empty": true, "size": 0}, {"name": "cloudflare/.wrangler/tmp", "dir": true, "empty": true, "size": 0}, {"name": "updaters", "dir": true, "empty": true, "size": 0}, {"name": "cloudflare/.wrangler/state/v3/d1/miniflare-D1DatabaseObject/aa9dbaeac8d2a5530159f7bd45b499bc21ff30cd84d734130c978f8eec1ddec1.sqlite-wal", "dir": true, "empty": true, "size": 0}, {"name": ".gitignore", "dir": false, "empty": false, "size": 83}, {"name": "404.html", "dir": false, "empty": false, "size": 1454}, {"name": "Albums/1 featured/are cranes and planes friends.jpg", "dir": false, "empty": false, "size": 1350702}, {"name": "Albums/1 featured/enzo in a pretty field.jpg", "dir": false, "empty": false, "size": 2642929}, {"name": "Albums/1 featured/fdu film set.JPG", "dir": false, "empty": false, "size": 862168}, {"name": "Albums/1 featured/first snow of 2026.jpg", "dir": false, "empty": false, "size": 1858472}, {"name": "Albums/1 featured/he does NOT have a driving licence.JPG", "dir": false, "empty": false, "size": 1215819}, {"name": "Albums/1 featured/kopaonik ski lift in summer.jpg", "dir": false, "empty": false, "size": 608988}, {"name": "Albums/1 featured/lamp that glitched the CCD, photo turned out fine.jpg", "dir": false, "empty": false, "size": 969527}, {"name": "Albums/1 featured/milan and nađa talking from far away.jpg", "dir": false, "empty": false, "size": 1293255}, {"name": "Albums/1 featured/mom, dad and enzo.jpg", "dir": false, "empty": false, "size": 1162410}, {"name": "Albums/1 featured/nenad praying for a better future™.jpg", "dir": false, "empty": false, "size": 37113}, {"name": "Albums/1 featured/pretty view after 35 minute nap in public transport.jpg", "dir": false, "empty": false, "size": 601075}, {"name": "Albums/1 featured/scraping paint off walls in skc.jpg", "dir": false, "empty": false, "size": 4599432}, {"name": "Albums/1 featured/strasbourg public transport.jpg", "dir": false, "empty": false, "size": 1807368}, {"name": "Albums/1 featured/unknown holding cat.jpg", "dir": false, "empty": false, "size": 821719}, {"name": "Albums/1 featured/view from a bathroom window.jpg", "dir": false, "empty": false, "size": 4182431}, {"name": "Albums/1 featured/view from pančić 2.jpg", "dir": false, "empty": false, "size": 344233}, {"name": "Albums/1 featured/željko, tito and paki.jpg", "dir": false, "empty": false, "size": 3843747}, {"name": "Albums/2 enzo/derp.jpg", "dir": false, "empty": false, "size": 2026690}, {"name": "Albums/2 enzo/enzo drying off.jpg", "dir": false, "empty": false, "size": 1884315}, {"name": "Albums/2 enzo/enzo in a pretty field.jpg", "dir": false, "empty": false, "size": 2642929}, {"name": "Albums/2 enzo/expresing disagreement.jpg", "dir": false, "empty": false, "size": 1233200}, {"name": "Albums/2 enzo/fetching the ball.jpg", "dir": false, "empty": false, "size": 1883844}, {"name": "Albums/2 enzo/it's gonna be a long bath.jpg", "dir": false, "empty": false, "size": 1911900}, {"name": "Albums/2 enzo/just enzo.jpg", "dir": false, "empty": false, "size": 2286000}, {"name": "Albums/2 enzo/sleeping on my knee.jpg", "dir": false, "empty": false, "size": 671312}, {"name": "Albums/2 enzo/tired of running.jpg", "dir": false, "empty": false, "size": 1688405}, {"name": "Albums/3 people/accidentally matched with rajko and marko.jpg", "dir": false, "empty": false, "size": 1053634}, {"name": "Albums/3 people/ajs nigrutin.jpg", "dir": false, "empty": false, "size": 1623962}, {"name": "Albums/3 people/andrej, čiča, strale and mađija.jpg", "dir": false, "empty": false, "size": 1147498}, {"name": "Albums/3 people/andrej.jpg", "dir": false, "empty": false, "size": 488870}, {"name": "Albums/3 people/anita and anastasija.jpg", "dir": false, "empty": false, "size": 4035788}, {"name": "Albums/3 people/anja architect.jpg", "dir": false, "empty": false, "size": 1170814}, {"name": "Albums/3 people/blamara.jpg", "dir": false, "empty": false, "size": 1277222}, {"name": "Albums/3 people/boki.jpg", "dir": false, "empty": false, "size": 1344198}, {"name": "Albums/3 people/che.jpg", "dir": false, "empty": false, "size": 1211897}, {"name": "Albums/3 people/cutie patootie vukthony.jpg", "dir": false, "empty": false, "size": 1301352}, {"name": "Albums/3 people/dad and enzo.jpg", "dir": false, "empty": false, "size": 1356544}, {"name": "Albums/3 people/danica and nađa.jpg", "dir": false, "empty": false, "size": 1639360}, {"name": "Albums/3 people/danica.jpg", "dir": false, "empty": false, "size": 1432181}, {"name": "Albums/3 people/dobrica.jpg", "dir": false, "empty": false, "size": 4544935}, {"name": "Albums/3 people/dume displaying the chair.jpg", "dir": false, "empty": false, "size": 1167588}, {"name": "Albums/3 people/dunja, strale, ana and čiča.jpg", "dir": false, "empty": false, "size": 1252032}, {"name": "Albums/3 people/dzoli.jpg", "dir": false, "empty": false, "size": 1338241}, {"name": "Albums/3 people/elena oceanman.jpg", "dir": false, "empty": false, "size": 1385889}, {"name": "Albums/3 people/EVIL aleks.jpg", "dir": false, "empty": false, "size": 1507968}, {"name": "Albums/3 people/gavrilo.jpg", "dir": false, "empty": false, "size": 1891278}, {"name": "Albums/3 people/ivana (left) and ivana (right).jpg", "dir": false, "empty": false, "size": 1088883}, {"name": "Albums/3 people/jovana.jpg", "dir": false, "empty": false, "size": 704283}, {"name": "Albums/3 people/magdalena.jpg", "dir": false, "empty": false, "size": 4220549}, {"name": "Albums/3 people/malnourished rajkovići and jovana.jpg", "dir": false, "empty": false, "size": 1067732}, {"name": "Albums/3 people/matej (left) and ivana (right).JPG", "dir": false, "empty": false, "size": 1447181}, {"name": "Albums/3 people/matej in the dark.jpg", "dir": false, "empty": false, "size": 968158}, {"name": "Albums/3 people/matej, during the same violent argument as the cocacola glass.jpg", "dir": false, "empty": false, "size": 1163749}, {"name": "Albums/3 people/matija.jpg", "dir": false, "empty": false, "size": 4248211}, {"name": "Albums/3 people/maša listening to piano music.jpg", "dir": false, "empty": false, "size": 1446059}, {"name": "Albums/3 people/mia.jpg", "dir": false, "empty": false, "size": 4492039}, {"name": "Albums/3 people/miksa.JPG", "dir": false, "empty": false, "size": 1064354}, {"name": "Albums/3 people/mila and ena.jpg", "dir": false, "empty": false, "size": 1455934}, {"name": "Albums/3 people/milamche selfie.jpg", "dir": false, "empty": false, "size": 4704840}, {"name": "Albums/3 people/milamche.jpg", "dir": false, "empty": false, "size": 4445526}, {"name": "Albums/3 people/milica.jpg", "dir": false, "empty": false, "size": 1336291}, {"name": "Albums/3 people/mogging.JPG", "dir": false, "empty": false, "size": 1156009}, {"name": "Albums/3 people/mom and enzo.jpg", "dir": false, "empty": false, "size": 828807}, {"name": "Albums/3 people/mom, dad, enzo and me.jpg", "dir": false, "empty": false, "size": 1409006}, {"name": "Albums/3 people/more money more grcka.jpg", "dir": false, "empty": false, "size": 1401840}, {"name": "Albums/3 people/nađa fasper.jpg", "dir": false, "empty": false, "size": 1411737}, {"name": "Albums/3 people/nenad.jpg", "dir": false, "empty": false, "size": 1710025}, {"name": "Albums/3 people/nešica.jpg", "dir": false, "empty": false, "size": 1371761}, {"name": "Albums/3 people/nina and jovana.JPG", "dir": false, "empty": false, "size": 1453391}, {"name": "Albums/3 people/olga zvučić.jpg", "dir": false, "empty": false, "size": 1187208}, {"name": "Albums/3 people/olga, grrrrr.jpg", "dir": false, "empty": false, "size": 1245694}, {"name": "Albums/3 people/pefan (2).JPG", "dir": false, "empty": false, "size": 1375120}, {"name": "Albums/3 people/pefan.jpg", "dir": false, "empty": false, "size": 990759}, {"name": "Albums/3 people/penis water gun (and šikuljak).jpg", "dir": false, "empty": false, "size": 1145199}, {"name": "Albums/3 people/petar and jovana.jpg", "dir": false, "empty": false, "size": 926959}, {"name": "Albums/3 people/rale breaking a chair just by sitting.jpg", "dir": false, "empty": false, "size": 1559261}, {"name": "Albums/3 people/relja raf, after saying something so unimaginably wise.jpg", "dir": false, "empty": false, "size": 927043}, {"name": "Albums/3 people/sava with toilet paper.JPG", "dir": false, "empty": false, "size": 1107707}, {"name": "Albums/3 people/sava.jpg", "dir": false, "empty": false, "size": 1082039}, {"name": "Albums/3 people/some kfc guys.jpg", "dir": false, "empty": false, "size": 902988}, {"name": "Albums/3 people/strale mađija and coa.jpg", "dir": false, "empty": false, "size": 2179014}, {"name": "Albums/3 people/tarik unamused.jpg", "dir": false, "empty": false, "size": 4521779}, {"name": "Albums/3 people/tarik.jpg", "dir": false, "empty": false, "size": 4855188}, {"name": "Albums/3 people/topalović pavle and me.jpg", "dir": false, "empty": false, "size": 1206035}, {"name": "Albums/3 people/una.JPG", "dir": false, "empty": false, "size": 1021344}, {"name": "Albums/3 people/velika tea.jpg", "dir": false, "empty": false, "size": 1502224}, {"name": "Albums/3 people/vukhtony rikhtano.jpg", "dir": false, "empty": false, "size": 1234431}, {"name": "Albums/3 people/what a working satellite sees before it becomes not that.jpg", "dir": false, "empty": false, "size": 1268075}, {"name": "Albums/3 people/yelena.jpg", "dir": false, "empty": false, "size": 1211832}, {"name": "Albums/3 people/čačakmačak.JPG", "dir": false, "empty": false, "size": 1304358}, {"name": "Albums/3 people/đorđe rektorović 2.jpg", "dir": false, "empty": false, "size": 1246397}, {"name": "Albums/3 people/đorđe rektorović.jpg", "dir": false, "empty": false, "size": 4312068}, {"name": "Albums/3 people/šava.jpg", "dir": false, "empty": false, "size": 4371943}, {"name": "Albums/4 cool photos/aesthetic mcdonalds.jpg", "dir": false, "empty": false, "size": 1170087}, {"name": "Albums/4 cool photos/bathroom wall.JPG", "dir": false, "empty": false, "size": 1092887}, {"name": "Albums/4 cool photos/birthday present for a friend.jpg", "dir": false, "empty": false, "size": 1195060}, {"name": "Albums/4 cool photos/charging the phone pigs couldnt confiscate.jpg", "dir": false, "empty": false, "size": 1654898}, {"name": "Albums/4 cool photos/dinner.jpg", "dir": false, "empty": false, "size": 2907092}, {"name": "Albums/4 cool photos/entrance to kalemegdan.jpg", "dir": false, "empty": false, "size": 2527100}, {"name": "Albums/4 cool photos/faculty.JPG", "dir": false, "empty": false, "size": 1767741}, {"name": "Albums/4 cool photos/filled this glass while people were violently arguing around me.jpg", "dir": false, "empty": false, "size": 1173365}, {"name": "Albums/4 cool photos/flowers.jpg", "dir": false, "empty": false, "size": 4112381}, {"name": "Albums/4 cool photos/found out i have dust inside the lens.jpg", "dir": false, "empty": false, "size": 1069045}, {"name": "Albums/4 cool photos/fresh mog.jpg", "dir": false, "empty": false, "size": 764073}, {"name": "Albums/4 cool photos/hello.jpg", "dir": false, "empty": false, "size": 1617756}, {"name": "Albums/4 cool photos/just stop to admire the clouds.jpg", "dir": false, "empty": false, "size": 1031922}, {"name": "Albums/4 cool photos/kst ain't ready for this.jpg", "dir": false, "empty": false, "size": 1580258}, {"name": "Albums/4 cool photos/lemon.jpg", "dir": false, "empty": false, "size": 1285942}, {"name": "Albums/4 cool photos/listening to clairo on the top of kopaonik.jpg", "dir": false, "empty": false, "size": 1066011}, {"name": "Albums/4 cool photos/most christian car i've seen.jpg", "dir": false, "empty": false, "size": 1482413}, {"name": "Albums/4 cool photos/music video recording.jpg", "dir": false, "empty": false, "size": 1176036}, {"name": "Albums/4 cool photos/nađa and danica saying hellooo.jpg", "dir": false, "empty": false, "size": 1639360}, {"name": "Albums/4 cool photos/nenad and zeka signiture move.jpg", "dir": false, "empty": false, "size": 1447700}, {"name": "Albums/4 cool photos/nenad will avenge sava.jpg", "dir": false, "empty": false, "size": 1675927}, {"name": "Albums/4 cool photos/nenad's balanced diet.jpg", "dir": false, "empty": false, "size": 28738}, {"name": "Albums/4 cool photos/nije TMF kunem se.JPG", "dir": false, "empty": false, "size": 1095459}, {"name": "Albums/4 cool photos/pretty clouds on kopaonik.jpg", "dir": false, "empty": false, "size": 1712741}, {"name": "Albums/4 cool photos/pretty sky from galerija.jpg", "dir": false, "empty": false, "size": 1279354}, {"name": "Albums/4 cool photos/pretty sky v3.jpg", "dir": false, "empty": false, "size": 1321618}, {"name": "Albums/4 cool photos/rainbow through polarized sunglasses.jpg", "dir": false, "empty": false, "size": 1279785}, {"name": "Albums/4 cool photos/sensor malfunction with sofija.jpg", "dir": false, "empty": false, "size": 4362713}, {"name": "Albums/4 cool photos/shortly after the sunrise,.jpg", "dir": false, "empty": false, "size": 1600021}, {"name": "Albums/4 cool photos/somebody did a whoopsie.jpg", "dir": false, "empty": false, "size": 1359598}, {"name": "Albums/4 cool photos/sunkissed building.jpg", "dir": false, "empty": false, "size": 1526165}, {"name": "Albums/4 cool photos/sunkissed buildings 2.jpg", "dir": false, "empty": false, "size": 1792652}, {"name": "Albums/4 cool photos/sunset.jpg", "dir": false, "empty": false, "size": 984135}, {"name": "Albums/4 cool photos/the best board game in all of bajina bašta.jpg", "dir": false, "empty": false, "size": 1780001}, {"name": "Albums/4 cool photos/the closest thing to a metro serbia will see v2.jpg", "dir": false, "empty": false, "size": 1090126}, {"name": "Albums/4 cool photos/the closest thing to a metro serbia will see v3.jpg", "dir": false, "empty": false, "size": 1533957}, {"name": "Albums/4 cool photos/the closest thing to a metro serbia will see.jpg", "dir": false, "empty": false, "size": 1390751}, {"name": "Albums/4 cool photos/the street while I was going to a test.JPG", "dir": false, "empty": false, "size": 1870762}, {"name": "Albums/4 cool photos/toilet we were caught not paying the entrance fee for.jpg", "dir": false, "empty": false, "size": 1003575}, {"name": "Albums/4 cool photos/train is late.JPG", "dir": false, "empty": false, "size": 1150140}, {"name": "Albums/4 cool photos/upside down clock in our high school.jpg", "dir": false, "empty": false, "size": 1097832}, {"name": "Albums/4 cool photos/ušće backrooms.jpg", "dir": false, "empty": false, "size": 1263633}, {"name": "Albums/4 cool photos/view from asiafood.jpg", "dir": false, "empty": false, "size": 1048907}, {"name": "Albums/4 cool photos/view from pančić.jpg", "dir": false, "empty": false, "size": 516458}, {"name": "Albums/4 cool photos/Warm brew - The Mission.jpg", "dir": false, "empty": false, "size": 1182511}, {"name": "Albums/5 petnica/a wizard's loot.JPG", "dir": false, "empty": false, "size": 1172079}, {"name": "Albums/5 petnica/boris' car cooling down.jpg", "dir": false, "empty": false, "size": 1488064}, {"name": "Albums/5 petnica/dont check the time of these photos.JPG", "dir": false, "empty": false, "size": 1697685}, {"name": "Albums/5 petnica/empty hallway.JPG", "dir": false, "empty": false, "size": 988857}, {"name": "Albums/5 petnica/heating the weather balloon.jpg", "dir": false, "empty": false, "size": 1426409}, {"name": "Albums/5 petnica/hotel walls.JPG", "dir": false, "empty": false, "size": 1030784}, {"name": "Albums/5 petnica/is lora working.jpg", "dir": false, "empty": false, "size": 1461087}, {"name": "Albums/5 petnica/me doing something very important.JPG", "dir": false, "empty": false, "size": 1245948}, {"name": "Albums/5 petnica/nina being cool.jpg", "dir": false, "empty": false, "size": 1194646}, {"name": "Albums/5 petnica/preparations for launch.jpg", "dir": false, "empty": false, "size": 1625387}, {"name": "Albums/5 petnica/pretty clouds in the sky.JPG", "dir": false, "empty": false, "size": 1661829}, {"name": "Albums/5 petnica/pretty view.JPG", "dir": false, "empty": false, "size": 965046}, {"name": "Albums/5 petnica/tour of a storage room.JPG", "dir": false, "empty": false, "size": 1156766}, {"name": "Albums/5 petnica/weather ballon, viktor for scale.jpg", "dir": false, "empty": false, "size": 1117768}, {"name": "Albums/5 petnica/wonderful people of our seminar.jpg", "dir": false, "empty": false, "size": 1751859}, {"name": "Albums/6 Film photos/andrej and me holding strale in a basketball hoop.JPG", "dir": false, "empty": false, "size": 6201804}, {"name": "Albums/6 Film photos/beach near rovinj.JPG", "dir": false, "empty": false, "size": 1800550}, {"name": "Albums/6 Film photos/birthday we crashed.JPG", "dir": false, "empty": false, "size": 7538567}, {"name": "Albums/6 Film photos/Botanical garden with mina.jpg", "dir": false, "empty": false, "size": 6653905}, {"name": "Albums/6 Film photos/burza with the same camera as me.JPG", "dir": false, "empty": false, "size": 6833079}, {"name": "Albums/6 Film photos/chevu and me.jpg", "dir": false, "empty": false, "size": 6564460}, {"name": "Albums/6 Film photos/chevulinko birthday.JPG", "dir": false, "empty": false, "size": 6893441}, {"name": "Albums/6 Film photos/dad and me in pula.JPG", "dir": false, "empty": false, "size": 2088638}, {"name": "Albums/6 Film photos/fairies and kratos, film set.JPG", "dir": false, "empty": false, "size": 7881397}, {"name": "Albums/6 Film photos/fallen.jpg", "dir": false, "empty": false, "size": 7843551}, {"name": "Albums/6 Film photos/fdu film set hangout.JPG", "dir": false, "empty": false, "size": 7885351}, {"name": "Albums/6 Film photos/highschool hallway.JPG", "dir": false, "empty": false, "size": 5522370}, {"name": "Albums/6 Film photos/inside the Petnica cave.jpg", "dir": false, "empty": false, "size": 7650249}, {"name": "Albums/6 Film photos/jopa broke a table.JPG", "dir": false, "empty": false, "size": 7244070}, {"name": "Albums/6 Film photos/last day of HS.JPG", "dir": false, "empty": false, "size": 5862121}, {"name": "Albums/6 Film photos/lukavac selfie.JPG", "dir": false, "empty": false, "size": 6166339}, {"name": "Albums/6 Film photos/me pefan and sava dogpile.JPG", "dir": false, "empty": false, "size": 7348507}, {"name": "Albums/6 Film photos/mom and me on a ski lift.JPG", "dir": false, "empty": false, "size": 5968587}, {"name": "Albums/6 Film photos/pavle dabbing unironically in 2023.JPG", "dir": false, "empty": false, "size": 6786308}, {"name": "Albums/6 Film photos/pavle's first gig.JPG", "dir": false, "empty": false, "size": 8229203}, {"name": "Albums/6 Film photos/petnica selfie.jpg", "dir": false, "empty": false, "size": 6274487}, {"name": "Albums/6 Film photos/simona and a swan.jpg", "dir": false, "empty": false, "size": 6676231}, {"name": "Albums/6 Film photos/sofija.JPG", "dir": false, "empty": false, "size": 7947954}, {"name": "Albums/6 Film photos/Strahinja and me.jpg", "dir": false, "empty": false, "size": 2171127}, {"name": "Albums/6 Film photos/tamara.jpg", "dir": false, "empty": false, "size": 7656827}, {"name": "Albums/6 Film photos/topalovic behind a wall with barbed wire.JPG", "dir": false, "empty": false, "size": 5111151}, {"name": "Albums/6 Film photos/topalovic tapping stefana with a loaf of bread.JPG", "dir": false, "empty": false, "size": 2351593}, {"name": "Albums/6 Film photos/topalovic VS luka epic fight.JPG", "dir": false, "empty": false, "size": 6054307}, {"name": "Albums/6 Film photos/trees i saw while laying in grass.JPG", "dir": false, "empty": false, "size": 6114488}, {"name": "Albums/6 Film photos/viktor ilegal MV.jpg", "dir": false, "empty": false, "size": 6884161}, {"name": "Albums/6 Film photos/viktor photobomb.jpg", "dir": false, "empty": false, "size": 6427693}, {"name": "Albums/6 Film photos/volleyball.jpg", "dir": false, "empty": false, "size": 5054275}, {"name": "Albums/6 Film photos/washing underwear in sarajevo.JPG", "dir": false, "empty": false, "size": 2233274}, {"name": "Albums/6 Film photos/zdravkovic panic and me.JPG", "dir": false, "empty": false, "size": 6079316}, {"name": "Albums/6 Film photos/zelena jelena.jpg", "dir": false, "empty": false, "size": 5889018}, {"name": "Albums/6 Film photos/čiča strale and kruška.jpg", "dir": false, "empty": false, "size": 6232642}, {"name": "Albums/7 blokade/blossoming tree from strasbourg.jpg", "dir": false, "empty": false, "size": 2735885}, {"name": "Albums/7 blokade/breakfast.jpg", "dir": false, "empty": false, "size": 1006810}, {"name": "Albums/7 blokade/bulgarian house in strasbourg.jpg", "dir": false, "empty": false, "size": 1557265}, {"name": "Albums/7 blokade/carrying a mattress.JPG", "dir": false, "empty": false, "size": 955179}, {"name": "Albums/7 blokade/Cathédrale Notre-Dame de Strasbourg.jpg", "dir": false, "empty": false, "size": 1637031}, {"name": "Albums/7 blokade/cleaned blankets.jpg", "dir": false, "empty": false, "size": 1518353}, {"name": "Albums/7 blokade/cyclists on a break.jpg", "dir": false, "empty": false, "size": 1365606}, {"name": "Albums/7 blokade/dinner made by delightful people on our way to strasbourg.jpg", "dir": false, "empty": false, "size": 1486689}, {"name": "Albums/7 blokade/drawing up a banner.jpg", "dir": false, "empty": false, "size": 948341}, {"name": "Albums/7 blokade/essentials for a photographer.jpg", "dir": false, "empty": false, "size": 934005}, {"name": "Albums/7 blokade/EU parliament building 2.jpg", "dir": false, "empty": false, "size": 891058}, {"name": "Albums/7 blokade/EU parliament building.jpg", "dir": false, "empty": false, "size": 1286174}, {"name": "Albums/7 blokade/EU parliament flags.jpg", "dir": false, "empty": false, "size": 1336004}, {"name": "Albums/7 blokade/faculty of philosophy instant ramen.jpg", "dir": false, "empty": false, "size": 1434772}, {"name": "Albums/7 blokade/field i ran through.jpg", "dir": false, "empty": false, "size": 1151057}, {"name": "Albums/7 blokade/grfmobile.jpg", "dir": false, "empty": false, "size": 1864577}, {"name": "Albums/7 blokade/hello djole.jpg", "dir": false, "empty": false, "size": 2076095}, {"name": "Albums/7 blokade/hidden wares of the philosophers.jpg", "dir": false, "empty": false, "size": 1803725}, {"name": "Albums/7 blokade/highschool hallway.jpg", "dir": false, "empty": false, "size": 1342125}, {"name": "Albums/7 blokade/if they could read they wouldnt be here.JPG", "dir": false, "empty": false, "size": 1044732}, {"name": "Albums/7 blokade/index film showing.jpg", "dir": false, "empty": false, "size": 1642189}, {"name": "Albums/7 blokade/last glimmers of hope for our highschool.jpg", "dir": false, "empty": false, "size": 1597509}, {"name": "Albums/7 blokade/late stage blockade beds.jpg", "dir": false, "empty": false, "size": 1740354}, {"name": "Albums/7 blokade/lunch.jpg", "dir": false, "empty": false, "size": 1071975}, {"name": "Albums/7 blokade/macintosh.jpg", "dir": false, "empty": false, "size": 1235995}, {"name": "Albums/7 blokade/manufacturing badges.jpg", "dir": false, "empty": false, "size": 1750102}, {"name": "Albums/7 blokade/mila's things.jpg", "dir": false, "empty": false, "size": 1359670}, {"name": "Albums/7 blokade/milica's rectorate logo.jpg", "dir": false, "empty": false, "size": 1769516}, {"name": "Albums/7 blokade/only the essentials for a trip in europe.jpg", "dir": false, "empty": false, "size": 1659828}, {"name": "Albums/7 blokade/pigs guarding garbage.jpg", "dir": false, "empty": false, "size": 1117136}, {"name": "Albums/7 blokade/rectorate cat đole.jpg", "dir": false, "empty": false, "size": 1246397}, {"name": "Albums/7 blokade/rectorate underground.jpg", "dir": false, "empty": false, "size": 1742403}, {"name": "Albums/7 blokade/state of rectorate 1.jpg", "dir": false, "empty": false, "size": 1406755}, {"name": "Albums/7 blokade/state of rectorate 2.jpg", "dir": false, "empty": false, "size": 1488819}, {"name": "Albums/7 blokade/strasbourg pretty pasageway.jpg", "dir": false, "empty": false, "size": 1767166}, {"name": "Albums/7 blokade/veterinarian faculty somehow still under blockade.jpg", "dir": false, "empty": false, "size": 1298668}, {"name": "Albums/7 blokade/wicked plans are brewing (beer).jpg", "dir": false, "empty": false, "size": 855882}, {"name": "Albums/8 iPhone/2013 taekwondo camp room.JPG", "dir": false, "empty": false, "size": 508817}, {"name": "Albums/8 iPhone/boki and me next to our fort of some sort.JPG", "dir": false, "empty": false, "size": 664244}, {"name": "Albums/8 iPhone/boki and me standing proud.JPG", "dir": false, "empty": false, "size": 677806}, {"name": "Albums/8 iPhone/boki covering me with snow.JPG", "dir": false, "empty": false, "size": 535308}, {"name": "Albums/8 iPhone/castle of magic screenshot.PNG", "dir": false, "empty": false, "size": 271356}, {"name": "Albums/8 iPhone/gavrilo and tanja.JPG", "dir": false, "empty": false, "size": 633697}, {"name": "Albums/8 iPhone/getting snow for our snowman.JPG", "dir": false, "empty": false, "size": 630612}, {"name": "Albums/8 iPhone/homescreen.PNG", "dir": false, "empty": false, "size": 108891}, {"name": "Albums/8 iPhone/masinci protiv masinerije.JPG", "dir": false, "empty": false, "size": 830267}, {"name": "Albums/8 iPhone/me falling.JPG", "dir": false, "empty": false, "size": 719296}, {"name": "Albums/8 iPhone/new flea market building.JPG", "dir": false, "empty": false, "size": 439393}, {"name": "Albums/8 iPhone/pigs.JPG", "dir": false, "empty": false, "size": 624104}, {"name": "Albums/8 iPhone/random homescreen screenshot.PNG", "dir": false, "empty": false, "size": 93816}, {"name": "Albums/8 iPhone/some protest.JPG", "dir": false, "empty": false, "size": 505099}, {"name": "Albums/8 iPhone/stankovic taking a photo of pigs.JPG", "dir": false, "empty": false, "size": 570376}, {"name": "assets/arrow.cur", "dir": false, "empty": false, "size": 4286}, {"name": "assets/arrow_1.cur", "dir": false, "empty": false, "size": 3262}, {"name": "assets/arrow_old.cur", "dir": false, "empty": false, "size": 326}, {"name": "assets/attic/captions.json", "dir": false, "empty": false, "size": 23365}, {"name": "assets/attic/photos-script.js", "dir": false, "empty": false, "size": 21519}, {"name": "assets/attic/script.js", "dir": false, "empty": false, "size": 32801}, {"name": "assets/attic/style.css", "dir": false, "empty": false, "size": 41591}, {"name": "assets/attic/update-photos.js", "dir": false, "empty": false, "size": 8074}, {"name": "assets/banner/.old/footer_00.webp", "dir": false, "empty": false, "size": 83758}, {"name": "assets/banner/.old/footer_01.webp", "dir": false, "empty": false, "size": 117898}, {"name": "assets/banner/.old/footer_02.webp", "dir": false, "empty": false, "size": 85686}, {"name": "assets/banner/.old/footer_03.webp", "dir": false, "empty": false, "size": 86174}, {"name": "assets/banner/.old/footer_04.webp", "dir": false, "empty": false, "size": 78572}, {"name": "assets/banner/.old/footer_05.webp", "dir": false, "empty": false, "size": 64446}, {"name": "assets/banner/.old/footer_06.webp", "dir": false, "empty": false, "size": 73010}, {"name": "assets/banner/.old/footer_07.webp", "dir": false, "empty": false, "size": 73890}, {"name": "assets/banner/.old/footer_08.webp", "dir": false, "empty": false, "size": 83144}, {"name": "assets/banner/.old/footer_09.webp", "dir": false, "empty": false, "size": 85984}, {"name": "assets/banner/.old/footer_1.webp", "dir": false, "empty": false, "size": 89896}, {"name": "assets/banner/.old/footer_10.webp", "dir": false, "empty": false, "size": 120634}, {"name": "assets/banner/.old/footer_2.webp", "dir": false, "empty": false, "size": 111302}, {"name": "assets/banner/banner_00.webp", "dir": false, "empty": false, "size": 76074}, {"name": "assets/banner/banner_01.webp", "dir": false, "empty": false, "size": 109714}, {"name": "assets/banner/banner_02.webp", "dir": false, "empty": false, "size": 92630}, {"name": "assets/banner/banner_03.webp", "dir": false, "empty": false, "size": 78790}, {"name": "assets/banner/banner_04.webp", "dir": false, "empty": false, "size": 70960}, {"name": "assets/banner/banner_05.webp", "dir": false, "empty": false, "size": 53354}, {"name": "assets/banner/banner_06.webp", "dir": false, "empty": false, "size": 58366}, {"name": "assets/banner/banner_07.webp", "dir": false, "empty": false, "size": 61774}, {"name": "assets/banner/banner_08.webp", "dir": false, "empty": false, "size": 75054}, {"name": "assets/banner/banner_09.webp", "dir": false, "empty": false, "size": 77490}, {"name": "assets/banner/banner_10.webp", "dir": false, "empty": false, "size": 111626}, {"name": "assets/Clairo_Charm.svg", "dir": false, "empty": false, "size": 24533}, {"name": "assets/counter-baked.js", "dir": false, "empty": false, "size": 149}, {"name": "assets/fire.gif", "dir": false, "empty": false, "size": 69063}, {"name": "assets/gear/camera 0.jpg", "dir": false, "empty": false, "size": 11462}, {"name": "assets/gear/camera 1.jpg", "dir": false, "empty": false, "size": 12522}, {"name": "assets/gear/camera 2.jpg", "dir": false, "empty": false, "size": 11446}, {"name": "assets/gear/camera 3.jpg", "dir": false, "empty": false, "size": 11033}, {"name": "assets/gear/camera 4.jpg", "dir": false, "empty": false, "size": 10923}, {"name": "assets/gear/gear-placeholder.svg", "dir": false, "empty": false, "size": 120}, {"name": "assets/gear/lens 1.jpg", "dir": false, "empty": false, "size": 14060}, {"name": "assets/gear/lens 2.jpg", "dir": false, "empty": false, "size": 8255}, {"name": "assets/gear/lens 3.jpg", "dir": false, "empty": false, "size": 8944}, {"name": "assets/gear/lens 4.jpg", "dir": false, "empty": false, "size": 8535}, {"name": "assets/gear/lens 5.jpg", "dir": false, "empty": false, "size": 7386}, {"name": "assets/gear/nothing headphones.jpg", "dir": false, "empty": false, "size": 11007}, {"name": "assets/gear/phone 1.jpg", "dir": false, "empty": false, "size": 10159}, {"name": "assets/gear/phone 2.jpg", "dir": false, "empty": false, "size": 9711}, {"name": "assets/gear/phone 3.jpg", "dir": false, "empty": false, "size": 7790}, {"name": "assets/gear/phone 4.jpg", "dir": false, "empty": false, "size": 9678}, {"name": "assets/gear/phone 5.jpg", "dir": false, "empty": false, "size": 12030}, {"name": "assets/gear/phone 6.jpg", "dir": false, "empty": false, "size": 10161}, {"name": "assets/gear/remarkable paper pro.jpg", "dir": false, "empty": false, "size": 10237}, {"name": "assets/guestbook-baked.js", "dir": false, "empty": false, "size": 20087}, {"name": "assets/guestbook-loader.js", "dir": false, "empty": false, "size": 25632}, {"name": "assets/holidays.js", "dir": false, "empty": false, "size": 9635}, {"name": "assets/html2canvas.min.js", "dir": false, "empty": false, "size": 198689}, {"name": "assets/icon.jpg", "dir": false, "empty": false, "size": 20907}, {"name": "assets/icon.png", "dir": false, "empty": false, "size": 285449}, {"name": "assets/lastfm-baked.js", "dir": false, "empty": false, "size": 91939}, {"name": "assets/ltremark/LTRemark-Black.otf", "dir": false, "empty": false, "size": 66752}, {"name": "assets/ltremark/LTRemark-BlackItalic.otf", "dir": false, "empty": false, "size": 75448}, {"name": "assets/ltremark/LTRemark-Bold.otf", "dir": false, "empty": false, "size": 67564}, {"name": "assets/ltremark/LTRemark-BoldItalic.otf", "dir": false, "empty": false, "size": 78484}, {"name": "assets/ltremark/LTRemark-Italic.otf", "dir": false, "empty": false, "size": 75052}, {"name": "assets/ltremark/LTRemark-Regular.otf", "dir": false, "empty": false, "size": 63596}, {"name": "assets/music-script.js", "dir": false, "empty": false, "size": 7467}, {"name": "assets/og-banner-image.jpg", "dir": false, "empty": false, "size": 259718}, {"name": "assets/other fonts/BlasterFont-Demo.otf", "dir": false, "empty": false, "size": 310716}, {"name": "assets/other fonts/CHETKIYTYPEFACE.otf", "dir": false, "empty": false, "size": 49128}, {"name": "assets/other fonts/comic-sans.ttf", "dir": false, "empty": false, "size": 126364}, {"name": "assets/other fonts/consolas.ttf", "dir": false, "empty": false, "size": 98520}, {"name": "assets/other fonts/Geist-Medium.otf", "dir": false, "empty": false, "size": 303761}, {"name": "assets/other fonts/HumanSans-Bold.otf", "dir": false, "empty": false, "size": 106056}, {"name": "assets/other fonts/HumanSans-Regular.otf", "dir": false, "empty": false, "size": 96896}, {"name": "assets/other fonts/Inter_28pt-Regular.ttf", "dir": false, "empty": false, "size": 342484}, {"name": "assets/other fonts/RobotoMono-Regular.ttf", "dir": false, "empty": false, "size": 87540}, {"name": "assets/other fonts/VCR_OSD_MONO_1.001.ttf", "dir": false, "empty": false, "size": 75864}, {"name": "assets/other fonts/WINGDNG3.TTF", "dir": false, "empty": false, "size": 35328}, {"name": "assets/photos-script.js", "dir": false, "empty": false, "size": 33106}, {"name": "assets/photos/alice-phoebe-lou.jpg", "dir": false, "empty": false, "size": 25439}, {"name": "assets/photos/arctic-monkeys.jpg", "dir": false, "empty": false, "size": 14248}, {"name": "assets/photos/clairo.jpg", "dir": false, "empty": false, "size": 13532}, {"name": "assets/photos/KMR4_DSG09192.jpg", "dir": false, "empty": false, "size": 53302}, {"name": "assets/photos/KMR5_DSG09536-ARW.jpg", "dir": false, "empty": false, "size": 74374}, {"name": "assets/photos/marias.jpg", "dir": false, "empty": false, "size": 8793}, {"name": "assets/photos/nadstresnica.jpg", "dir": false, "empty": false, "size": 123606}, {"name": "assets/photos/oslobodjenje_rektorata.jpg", "dir": false, "empty": false, "size": 93282}, {"name": "assets/photos/slobodan_masinac.jpg", "dir": false, "empty": false, "size": 74317}, {"name": "assets/photos/the-strokes.jpg", "dir": false, "empty": false, "size": 5810}, {"name": "assets/photos/tyler-the-creator.jpg", "dir": false, "empty": false, "size": 19395}, {"name": "assets/pointer.cur", "dir": false, "empty": false, "size": 4286}, {"name": "assets/pointer_1.cur", "dir": false, "empty": false, "size": 3262}, {"name": "assets/pointer_old.cur", "dir": false, "empty": false, "size": 326}, {"name": "assets/redaction/Redaction-Bold.otf", "dir": false, "empty": false, "size": 49720}, {"name": "assets/redaction/Redaction-Italic.otf", "dir": false, "empty": false, "size": 51512}, {"name": "assets/redaction/Redaction-Regular.otf", "dir": false, "empty": false, "size": 48940}, {"name": "assets/redaction/Redaction10-Bold.otf", "dir": false, "empty": false, "size": 91212}, {"name": "assets/redaction/Redaction10-Italic.otf", "dir": false, "empty": false, "size": 110948}, {"name": "assets/redaction/Redaction10-Regular.otf", "dir": false, "empty": false, "size": 88724}, {"name": "assets/redaction/Redaction20-Bold.otf", "dir": false, "empty": false, "size": 56620}, {"name": "assets/redaction/Redaction20-Italic.otf", "dir": false, "empty": false, "size": 65212}, {"name": "assets/redaction/Redaction20-Regular.otf", "dir": false, "empty": false, "size": 55228}, {"name": "assets/redaction/Redaction35-Bold.otf", "dir": false, "empty": false, "size": 42148}, {"name": "assets/redaction/Redaction35-Italic.otf", "dir": false, "empty": false, "size": 46020}, {"name": "assets/redaction/Redaction35-Regular.otf", "dir": false, "empty": false, "size": 40736}, {"name": "assets/script.js", "dir": false, "empty": false, "size": 74967}, {"name": "assets/server.js", "dir": false, "empty": false, "size": 3620}, {"name": "assets/share.svg", "dir": false, "empty": false, "size": 702}, {"name": "assets/shared.js", "dir": false, "empty": false, "size": 4499}, {"name": "assets/style.css", "dir": false, "empty": false, "size": 73685}, {"name": "assets/update-counter.js", "dir": false, "empty": false, "size": 2470}, {"name": "assets/update-guestbook.js", "dir": false, "empty": false, "size": 6832}, {"name": "assets/update-photos.js", "dir": false, "empty": false, "size": 22365}, {"name": "assets/update-tunes.js", "dir": false, "empty": false, "size": 9886}, {"name": "assets/valjdaslike.jpg", "dir": false, "empty": false, "size": 31419}, {"name": "assets/wallpaper.jpg", "dir": false, "empty": false, "size": 166876}, {"name": "cloudflare/.wrangler/cache/cf.json", "dir": false, "empty": false, "size": 1949}, {"name": "cloudflare/.wrangler/cache/wrangler-account.json", "dir": false, "empty": false, "size": 118}, {"name": "cloudflare/.wrangler/state/v3/d1/miniflare-D1DatabaseObject/aa9dbaeac8d2a5530159f7bd45b499bc21ff30cd84d734130c978f8eec1ddec1.sqlite", "dir": false, "empty": false, "size": 4096}, {"name": "cloudflare/.wrangler/state/v3/d1/miniflare-D1DatabaseObject/aa9dbaeac8d2a5530159f7bd45b499bc21ff30cd84d734130c978f8eec1ddec1.sqlite-shm", "dir": false, "empty": false, "size": 32768}, {"name": "cloudflare/.wrangler/state/v3/d1/miniflare-D1DatabaseObject/metadata.sqlite", "dir": false, "empty": false, "size": 4096}, {"name": "cloudflare/.wrangler/state/v3/d1/miniflare-D1DatabaseObject/metadata.sqlite-shm", "dir": false, "empty": false, "size": 32768}, {"name": "cloudflare/.wrangler/state/v3/d1/miniflare-D1DatabaseObject/metadata.sqlite-wal", "dir": false, "empty": false, "size": 8272}, {"name": "cloudflare/deploy.bat", "dir": false, "empty": false, "size": 49}, {"name": "cloudflare/schema.sql", "dir": false, "empty": false, "size": 677}, {"name": "cloudflare/setup.bat", "dir": false, "empty": false, "size": 818}, {"name": "cloudflare/worker.js", "dir": false, "empty": false, "size": 1211204}, {"name": "cloudflare/wrangler.toml", "dir": false, "empty": false, "size": 189}, {"name": "evil_index.html", "dir": false, "empty": false, "size": 25685}, {"name": "evil_photos.html", "dir": false, "empty": false, "size": 5130}, {"name": "gear.html", "dir": false, "empty": false, "size": 23166}, {"name": "guestbook.html", "dir": false, "empty": false, "size": 31514}, {"name": "index.html", "dir": false, "empty": false, "size": 31370}, {"name": "memorial.html", "dir": false, "empty": false, "size": 4980}, {"name": "music.html", "dir": false, "empty": false, "size": 13227}, {"name": "photos.html", "dir": false, "empty": false, "size": 16658}, {"name": "privacy.html", "dir": false, "empty": false, "size": 36709}, {"name": "robots.txt", "dir": false, "empty": false, "size": 73}, {"name": "server.bat", "dir": false, "empty": false, "size": 426}, {"name": "share.html", "dir": false, "empty": false, "size": 20743}, {"name": "sitemap.xml", "dir": false, "empty": false, "size": 1258}, {"name": "sw.js", "dir": false, "empty": false, "size": 2351}, {"name": "test.html", "dir": false, "empty": false, "size": 5062}, {"name": "update-all.bat", "dir": false, "empty": false, "size": 2395}, {"name": "updaters/save.bat", "dir": false, "empty": false, "size": 1271}, {"name": "updaters/update-counter.bat", "dir": false, "empty": false, "size": 137}, {"name": "updaters/update-guestbook.bat", "dir": false, "empty": false, "size": 141}, {"name": "updaters/update-photos.bat", "dir": false, "empty": false, "size": 130}, {"name": "updaters/update-tunes.bat", "dir": false, "empty": false, "size": 133}, {"name": "videos.html", "dir": false, "empty": false, "size": 10208}, {"name": "_headers", "dir": false, "empty": false, "size": 265}]